appl/__init__.py
appl/caching/__init__.py
appl/caching/db.py
appl/caching/utils.py
appl/cli/__init__.py
appl/cli/vis_trace.py
appl/compositor.py
appl/const.py
appl/core/__init__.py
appl/core/compile.py
appl/core/config.py
appl/core/context.py
appl/core/function.py
appl/core/generation.py
appl/core/globals.py
appl/core/io.py
appl/core/message.py
appl/core/modifiers.py
appl/core/patch.py
appl/core/printer.py
appl/core/promptable/__init__.py
appl/core/promptable/base.py
appl/core/promptable/definition.py
appl/core/promptable/formatter.py
appl/core/response.py
appl/core/runtime.py
appl/core/server.py
appl/core/tool.py
appl/core/trace.py
appl/core/types/__init__.py
appl/core/types/basic.py
appl/core/types/caching.py
appl/core/types/content.py
appl/core/types/custom.py
appl/core/types/executor.py
appl/core/types/futures.py
appl/core/types/role.py
appl/core/types/trace.py
appl/core/utils.py
appl/default_configs.yaml
appl/func.py
appl/py.typed
appl/role_changer.py
appl/servers/__init__.py
appl/servers/api.py
appl/servers/manager.py
appl/settings.py
appl/tracing/__init__.py
appl/tracing/engine.py
appl/tracing/header.html
appl/tracing/printer.py
appl/tracing/tmp_TODO.md
appl/types.py
appl/utils.py
appl/version.py
applang-0.2.2.dist-info/METADATA
applang-0.2.2.dist-info/WHEEL
applang-0.2.2.dist-info/entry_points.txt
applang-0.2.2.dist-info/licenses/LICENSE
applang-0.2.2.dist-info/RECORD
