Metadata-Version: 2.1
Name: applang
Version: 0.2.2
Summary: A Prompt Programming Language
Author-Email: Honghua Dong <dhh19951@gmail.com>, QiDong Su <soodoshll@gmail.com>, Jim Gao <ybgao@cs.toronto.edu>
License: MIT
Classifier: License :: OSI Approved :: MIT License
Classifier: Operating System :: OS Independent
Classifier: Programming Language :: Python
Classifier: Programming Language :: Python :: 3
Classifier: Programming Language :: Python :: 3 :: Only
Classifier: Programming Language :: Python :: 3.9
Classifier: Programming Language :: Python :: 3.10
Classifier: Programming Language :: Python :: 3.11
Classifier: Programming Language :: Python :: 3.12
Classifier: Programming Language :: Python :: 3.13
Classifier: Topic :: Scientific/Engineering :: Artificial Intelligence
Classifier: Typing :: Typed
Project-URL: Homepage, https://github.com/appl-team/appl
Requires-Python: >=3.9
Requires-Dist: loguru>=0.7.2
Requires-Dist: roman>=4.1
Requires-Dist: python-dotenv>=1.0.0
Requires-Dist: openai>=1.13.3
Requires-Dist: pydantic>=2.6.3
Requires-Dist: docstring-parser>=0.15
Requires-Dist: inflection>=0.5.1
Requires-Dist: PyYAML>=6.0.1
Requires-Dist: toml>=0.10.2
Requires-Dist: termcolor>=2.4.0
Requires-Dist: litellm>=1.59.8
Requires-Dist: tiktoken>=0.6.0
Requires-Dist: addict>=2.4.0
Requires-Dist: pendulum>=3.0.0
Requires-Dist: libcst>=1.4.0
Requires-Dist: rich>=13.8.1
Requires-Dist: pillow>=11.0.0
Requires-Dist: deprecated>=1.2.15
Requires-Dist: jsonargparse>=4.35.0
Provides-Extra: ext
Requires-Dist: lunary>=1.0.36; extra == "ext"
Requires-Dist: instructor>=1.5.2; extra == "ext"
Requires-Dist: langfuse>=2.56.1; extra == "ext"
